__init__.py
glp_model_matrix.py
gsl_bspline.py
mgcv_tensor.py
npiv.py
prodspline.py
test_engel.py
util_npiv.py
npiv_python-0.1.0.dist-info/METADATA
npiv_python-0.1.0.dist-info/WHEEL
npiv_python-0.1.0.dist-info/top_level.txt
npiv_python-0.1.0.dist-info/RECORD
