Metadata-Version: 2.4
Name: npiv-python
Version: 0.1.0
Summary: Nonparametric IV (NPIV) estimation in Python
Author-email: Anzony Quispe Rojas <anzony.quispe@gmail.com>
Project-URL: Homepage, https://github.com/youruser/npivlib
Classifier: Programming Language :: Python :: 3
Classifier: License :: OSI Approved :: MIT License
Classifier: Operating System :: OS Independent
Requires-Python: >=3.8
Requires-Dist: numpy
Requires-Dist: scipy
Requires-Dist: matplotlib
Requires-Dist: pandas
Requires-Dist: tqdm
Requires-Dist: patsy
